testapp/__init__.py
testapp/factories.py
testapp/models.py
testapp/schema.py
testapp/serializers.py
testapp/settings.py
testapp/urls.py
testapp/views.py
testapp/viewsets.py
testapp/migrations/0001_initial.py
testapp/migrations/0002_auto_20190620_0849.py
testapp/migrations/0003_person__etag.py
testapp/migrations/0004_auto_20190909_0206.py
testapp/migrations/0005_group_name.py
testapp/migrations/__init__.py
vng_api_common/__init__.py
vng_api_common/admin.py
vng_api_common/apps.py
vng_api_common/checks.py
vng_api_common/compat.py
vng_api_common/constants.py
vng_api_common/decorators.py
vng_api_common/descriptors.py
vng_api_common/exception_handling.py
vng_api_common/exceptions.py
vng_api_common/fields.py
vng_api_common/filters.py
vng_api_common/filtersets.py
vng_api_common/generators.py
vng_api_common/geo.py
vng_api_common/middleware.py
vng_api_common/mocks.py
vng_api_common/models.py
vng_api_common/oas.py
vng_api_common/permissions.py
vng_api_common/polymorphism.py
vng_api_common/routers.py
vng_api_common/schema.py
vng_api_common/scopes.py
vng_api_common/search.py
vng_api_common/serializers.py
vng_api_common/urls.py
vng_api_common/utils.py
vng_api_common/validators.py
vng_api_common/version.py
vng_api_common/views.py
vng_api_common/viewsets.py
vng_api_common/api/__init__.py
vng_api_common/api/serializers.py
vng_api_common/api/urls.py
vng_api_common/api/views.py
vng_api_common/audittrails/__init__.py
vng_api_common/audittrails/admin.py
vng_api_common/audittrails/apps.py
vng_api_common/audittrails/audits.py
vng_api_common/audittrails/models.py
vng_api_common/audittrails/viewsets.py
vng_api_common/audittrails/api/__init__.py
vng_api_common/audittrails/api/scopes.py
vng_api_common/audittrails/api/serializers.py
vng_api_common/audittrails/migrations/0001_initial.py
vng_api_common/audittrails/migrations/0002_auto_20190516_0830.py
vng_api_common/audittrails/migrations/0003_auto_20190517_0844.py
vng_api_common/audittrails/migrations/0004_auto_20190520_1238.py
vng_api_common_utrecht-1.3.2.dist-info/METADATA
vng_api_common_utrecht-1.3.2.dist-info/WHEEL
vng_api_common_utrecht-1.3.2.dist-info/top_level.txt
vng_api_common_utrecht-1.3.2.dist-info/RECORD
