Metadata-Version: 2.1
Name: vng-api-common-utrecht
Version: 1.3.2
Summary: VNG API tooling
Home-page: https://github.com/GemeenteUtrecht/vng-api-common
Author: Maykin Media, VNG-Realisatie
Author-email: support@maykinmedia.nl
License: EUPL 1.2
Keywords: openapi,swagger,django,vng
Platform: UNKNOWN
Classifier: Development Status :: 5 - Production/Stable
Classifier: Framework :: Django
Classifier: Framework :: Django :: 2.1
Classifier: Framework :: Django :: 2.2
Classifier: Intended Audience :: Developers
Classifier: Operating System :: Unix
Classifier: Operating System :: MacOS
Classifier: Operating System :: Microsoft :: Windows
Classifier: Programming Language :: Python :: 3.6
Classifier: Programming Language :: Python :: 3.7
Classifier: Topic :: Software Development :: Libraries :: Python Modules
Requires-Dist: django
Requires-Dist: django-choices
Requires-Dist: django-filter (>=2.0)
Requires-Dist: django-solo
Requires-Dist: djangorestframework (<3.10)
Requires-Dist: djangorestframework-camel-case
Requires-Dist: django-rest-framework-condition
Requires-Dist: drf-yasg (==1.16.0)
Requires-Dist: drf-nested-routers
Requires-Dist: gemma-zds-client (>=0.9.4)
Requires-Dist: iso-639
Requires-Dist: isodate
Requires-Dist: oyaml
Requires-Dist: PyJWT
Requires-Dist: pyyaml
Requires-Dist: requests
Requires-Dist: unidecode
Provides-Extra: coverage
Requires-Dist: pytest-cov ; extra == 'coverage'
Provides-Extra: docs
Requires-Dist: psycopg2 ; extra == 'docs'
Requires-Dist: sphinx ; extra == 'docs'
Requires-Dist: sphinx-rtd-theme ; extra == 'docs'
Provides-Extra: notifications
Provides-Extra: pep8
Requires-Dist: flake8 ; extra == 'pep8'
Provides-Extra: release
Requires-Dist: bumpversion ; extra == 'release'
Provides-Extra: tests
Requires-Dist: psycopg2 ; extra == 'tests'
Requires-Dist: pytest ; extra == 'tests'
Requires-Dist: pytest-django ; extra == 'tests'
Requires-Dist: pytest-factoryboy ; extra == 'tests'
Requires-Dist: tox ; extra == 'tests'
Requires-Dist: isort ; extra == 'tests'
Requires-Dist: black ; extra == 'tests'
Requires-Dist: requests-mock ; extra == 'tests'
